LICENSE
MANIFEST.in
README.md
setup.py
multisync/__init__.py
multisync/__init__.pyc
multisync/command.py
multisync/deb_fixes.py
multisync/defaults.py
multisync/defaults.pyc
multisync/django_synchronizers.py
multisync/gitlab_synchronizers.py
multisync/iniconf.py
multisync/iniconf.pyc
multisync/ldap_synchronizers.py
multisync/models.py
multisync/models.pyc
multisync/nrpe.py
multisync/prosody_synchronizers.py
multisync/root_urls.py
multisync/root_urls.pyc
multisync/synchronizer.py
multisync.egg-info/PKG-INFO
multisync.egg-info/SOURCES.txt
multisync.egg-info/dependency_links.txt
multisync.egg-info/entry_points.txt
multisync.egg-info/not-zip-safe
multisync.egg-info/requires.txt
multisync.egg-info/top_level.txt
multisync/templates/multisync/dev/deb-debian-8_ubuntu-14.10-15.10.sh_tpl
multisync/templates/multisync/dev/stdeb-debian-8_ubuntu-14.10-15.10.cfg_tpl
multisync/templates/multisync/dev/doc/source/installation.rst_tpl
multisync/templates/multisync/dev/vagrant/debian-8/Vagrantfile_tpl
multisync/templates/multisync/dev/vagrant/ubuntu-15.04/Vagrantfile_tpl
multisync/templates/multisync/dev/vagrant/ubuntu-15.10/Vagrantfile_tpl
multisync/tests/__init__.py
multisync/tests/test_django_synchronizers.py