Metadata-Version: 1.0
Name: multisync
Version: 0.5.3
Summary: No description yet.
Home-page: UNKNOWN
Author: Matthieu Gallet
Author-email: github@19pouces.net
License: CeCILL-B
Platform: UNKNOWN
